MANIFEST.in
VERSION
setup.py
xsanio_server/__init__.py
xsanio_server/manage.py
xsanio_server.egg-info/PKG-INFO
xsanio_server.egg-info/SOURCES.txt
xsanio_server.egg-info/dependency_links.txt
xsanio_server.egg-info/not-zip-safe
xsanio_server.egg-info/requires.txt
xsanio_server.egg-info/top_level.txt
xsanio_server/backend/__init__.py
xsanio_server/backend/models.py
xsanio_server/backend/tests.py
xsanio_server/backend/xsanio_backend.py
xsanio_server/backend/management/__init__.py
xsanio_server/backend/management/commands/__init__.py
xsanio_server/backend/management/commands/run_xsanio_backend.py
xsanio_server/mainapp/__init__.py
xsanio_server/mainapp/admin.py
xsanio_server/mainapp/models.py
xsanio_server/mainapp/tests.py
xsanio_server/mainapp/fixtures/initial_data.xml
xsanio_server/mainapp/views/__init__.py
xsanio_server/mainapp/views/client.py
xsanio_server/mainapp/views/grand_total.py
xsanio_server/mainapp/views/volume.py
xsanio_server/templates/base.html
xsanio_server/templates/client_detail.html
xsanio_server/templates/client_list.html
xsanio_server/templates/home.html
xsanio_server/templates/volume_detail.html
xsanio_server/templates/volume_list.html
xsanio_server/xsanio_server/__init__.py
xsanio_server/xsanio_server/settings.py
xsanio_server/xsanio_server/urls.py
xsanio_server/xsanio_server/wsgi.py