Metadata-Version: 1.0
Name: xsanio-server
Version: 0.8.4
Summary: Mac OS X Server Xsan I/O load monitoring tool
Home-page: UNKNOWN
Author: Vasily Kolosov
Author-email: vasily.kolosov@shortcut.ru
License: UNKNOWN
Platform: UNKNOWN
